lled.py
setup.cfg
setup.py
mookfist_lled_controller/__init__.py
mookfist_lled_controller/bridge.py
mookfist_lled_controller/cli.py
mookfist_lled_controller/colors.py
mookfist_lled_controller/exceptions.py
mookfist_lled_controller/logger.py
mookfist_lled_controller.egg-info/PKG-INFO
mookfist_lled_controller.egg-info/SOURCES.txt
mookfist_lled_controller.egg-info/dependency_links.txt
mookfist_lled_controller.egg-info/requires.txt
mookfist_lled_controller.egg-info/top_level.txt
mookfist_lled_controller/bridges/__init__.py
mookfist_lled_controller/bridges/ver4.py
mookfist_lled_controller/bridges/ver6.py
tests/__init__.py
tests/test_bridge.py
tests/test_colors.py
tests/test_command.py