Metadata-Version: 1.1
Name: mookfist-lled-controller
Version: 0.1.3
Summary: A python library for communicating with LimitlessLED/Milight/Easybulb compatible wifi bridges.
Home-page: https://github.com/mookfist/mookfist-lled-controller
Author: mookfist
Author-email: mookfist@gmail.com
License: UNKNOWN
Keywords: milight,limitlessled
Platform: UNKNOWN
Classifier: Development Status :: 5 - Production/Stable
Classifier: Intended Audience :: Developers
Classifier: Topic :: Utilities
Classifier: License :: OSI Approved :: MIT License
Classifier: Programming Language :: Python :: 2.7
Classifier: Programming Language :: Python :: 3
